auroradb/api/api.py
auroradb/scratch/encdec.py
auroradb/src/client.py
auroradb/test/test_api.py
auroradb/test/test_client.py
auroradb-0.0.2.dist-info/licenses/LICENSE
auroradb-0.0.2.dist-info/METADATA
auroradb-0.0.2.dist-info/WHEEL
auroradb-0.0.2.dist-info/top_level.txt
auroradb-0.0.2.dist-info/RECORD
